{
	"name": "MAP",
	"layers": [
		{
			"name": "tile_grass",
			"overriden": 0,
			"subLayers": [],
			"instances": [
				{
					"type": "TileMapGrass",
					"properties": {
						"initially-visible": true,
						"tile-width": 32,
						"tile-height": 32,
						"tile-x-offset": 0,
						"tile-y-offset": 0,
						"tile-x-spacing": 0,
						"tile-y-spacing": 0,
						"tile-x-drawing-offset": 0,
						"tile-y-drawing-offset": 0,
						"drawing-mode": "top-to-right"
					},
					"uid": 148,
					"instanceVariables": {},
					"behaviors": {},
					"ownData": {
						"tilemapData": {
							"width": 12,
							"height": 40,
							"max-width": 17,
							"max-height": 40,
							"data": "21x21,3x46,10x18,2x46,3x18,29,11x21,1,21,1,21,4x29,1,21,46,2x29,3x1,5x18,46,2x18,33,2x11,18,29,21,2x29,21,6x33,9x1,7x33,1,46,18,55,2x18,46,2x18,33,2x11,18,29,21,29,46,21,2x1,21,2x1,33,5x1,2x46,2x1,33,46,6x1,46,2x55,2x18,46,2x29,33,2x11,18,29,21,2x1,2x21,2x1,46,1,33,29,8x1,33,46,6x1,42,2x55,4x1,29,33,2x11,18,29,21,29,3x1,21,1,21,1,33,9x1,33,46,2x1,46,3x1,33,2x1,2x29,46,1,64,33,2x11,18,29,21,29,46,21,1,21,1,46,1,33,29,14x1,29,1,33,1,55,18,29,46,1,64,33,2x11,2x29,21,29,46,21,3x1,21,1,33,46,2x1,46,2x1,2x29,3x46,4x1,2x55,33,55,1,64,2x46,1,64,33,11,3x29,21,46,29,21,46,5x1,2x46,1,46,29,3x1,46,33,2x46,2x1,2x55,1,33,18,2x1,2x64,2x1,33,2x11,2x29,21,2x46,21,46,2x1,46,21,1,10x33,2x18,29,55,3x18,7x33,1,29,2x11,2x29,10x21,3x1,6x21,2x46,2x18,7x55,2x21,3x1,5x29,40x1,200x0"
						},
						"tile-width": 32,
						"tile-height": 32,
						"tile-x-offset": 0,
						"tile-y-offset": 0,
						"tile-x-spacing": 0,
						"tile-y-spacing": 0
					},
					"world": {
						"x": 0,
						"y": 0,
						"width": 385,
						"height": 1280,
						"originX": 0,
						"originY": 0,
						"color": [
							1,
							1,
							1,
							1
						],
						"zElevation": 0
					}
				}
			],
			"sid": 338897657850149,
			"effectTypes": [],
			"isInitiallyVisible": true,
			"isInitiallyInteractive": true,
			"color": [
				1,
				1,
				1,
				1
			],
			"backgroundColor": [
				1,
				1,
				1,
				1
			],
			"isTransparent": false,
			"parallaxX": 1,
			"parallaxY": 1,
			"scaleRate": 1,
			"forceOwnTexture": false,
			"renderingMode": "3d",
			"drawOrder": "z-order",
			"useRenderCells": false,
			"blendMode": "normal",
			"zElevation": 0,
			"global": false
		},
		{
			"name": "tile_map",
			"overriden": 0,
			"subLayers": [],
			"instances": [],
			"sid": 793681997706252,
			"effectTypes": [],
			"isInitiallyVisible": true,
			"isInitiallyInteractive": true,
			"color": [
				1,
				1,
				1,
				1
			],
			"backgroundColor": [
				1,
				1,
				1,
				1
			],
			"isTransparent": true,
			"parallaxX": 1,
			"parallaxY": 1,
			"scaleRate": 1,
			"forceOwnTexture": false,
			"renderingMode": "3d",
			"drawOrder": "z-order",
			"useRenderCells": false,
			"blendMode": "normal",
			"zElevation": 0,
			"global": false
		},
		{
			"name": "map_levels",
			"overriden": 0,
			"subLayers": [],
			"instances": [
				{
					"type": "obj_level_1",
					"properties": {
						"initially-visible": true,
						"initial-animation": "Animation 1",
						"initial-frame": 0,
						"enable-collisions": true,
						"live-preview": false
					},
					"uid": 181,
					"instanceVariables": {},
					"behaviors": {},
					"world": {
						"x": 48,
						"y": 127,
						"width": 64,
						"height": 85,
						"originX": 0,
						"originY": 1,
						"color": [
							1,
							1,
							1,
							1
						],
						"angle": 0,
						"zElevation": 0
					}
				},
				{
					"type": "obj_level_2",
					"properties": {
						"initially-visible": true,
						"initial-animation": "Animation 1",
						"initial-frame": 0,
						"enable-collisions": true,
						"live-preview": false
					},
					"uid": 182,
					"instanceVariables": {},
					"behaviors": {},
					"world": {
						"x": 259,
						"y": 320,
						"width": 64,
						"height": 85,
						"originX": 0,
						"originY": 1,
						"color": [
							1,
							1,
							1,
							1
						],
						"angle": 0,
						"zElevation": 0
					}
				},
				{
					"type": "obj_level_3",
					"properties": {
						"initially-visible": true,
						"initial-animation": "Animation 1",
						"initial-frame": 0,
						"enable-collisions": true,
						"live-preview": false
					},
					"uid": 183,
					"instanceVariables": {},
					"behaviors": {},
					"world": {
						"x": 197,
						"y": 658,
						"width": 64,
						"height": 85,
						"originX": 0,
						"originY": 1,
						"color": [
							1,
							1,
							1,
							1
						],
						"angle": 0,
						"zElevation": 0
					}
				},
				{
					"type": "obj_level_4",
					"properties": {
						"initially-visible": true,
						"initial-animation": "Animation 1",
						"initial-frame": 0,
						"enable-collisions": true,
						"live-preview": false
					},
					"uid": 184,
					"instanceVariables": {},
					"behaviors": {},
					"world": {
						"x": 59,
						"y": 898,
						"width": 64,
						"height": 85,
						"originX": 0,
						"originY": 1,
						"color": [
							1,
							1,
							1,
							1
						],
						"angle": 0,
						"zElevation": 0
					}
				},
				{
					"type": "obj_level_5",
					"properties": {
						"initially-visible": true,
						"initial-animation": "Animation 1",
						"initial-frame": 0,
						"enable-collisions": true,
						"live-preview": false
					},
					"uid": 185,
					"instanceVariables": {},
					"behaviors": {},
					"world": {
						"x": 270,
						"y": 1149,
						"width": 64,
						"height": 85,
						"originX": 0,
						"originY": 1,
						"color": [
							1,
							1,
							1,
							1
						],
						"angle": 0,
						"zElevation": 0
					}
				}
			],
			"sid": 707713951972790,
			"effectTypes": [],
			"isInitiallyVisible": true,
			"isInitiallyInteractive": true,
			"color": [
				1,
				1,
				1,
				1
			],
			"backgroundColor": [
				1,
				1,
				1,
				1
			],
			"isTransparent": true,
			"parallaxX": 1,
			"parallaxY": 1,
			"scaleRate": 1,
			"forceOwnTexture": false,
			"renderingMode": "3d",
			"drawOrder": "z-order",
			"useRenderCells": false,
			"blendMode": "normal",
			"zElevation": 0,
			"global": false
		},
		{
			"name": "text",
			"overriden": 0,
			"subLayers": [],
			"instances": [
				{
					"type": "txt_level_num",
					"properties": {
						"text": "1",
						"enable-bbcode": true,
						"font": "Capture_it",
						"size": 12,
						"line-height": 0,
						"bold": true,
						"italic": false,
						"color": [
							0.6666666666666666,
							0.6666666666666666,
							0.6666666666666666,
							1
						],
						"horizontal-alignment": "center",
						"vertical-alignment": "center",
						"wrapping": "word",
						"initially-visible": true,
						"origin": "top-left"
					},
					"uid": 186,
					"instanceVariables": {},
					"behaviors": {},
					"template": {
						"mode": "template",
						"templateName": "txt_level_numbering",
						"sourceTemplateName": "",
						"components": [
							{
								"id": "plugin",
								"component": [
									{
										"key": "plugin",
										"state": [
											[
												"text",
												true
											],
											[
												"enable-bbcode",
												true
											],
											[
												"font",
												true
											],
											[
												"size",
												true
											],
											[
												"line-height",
												true
											],
											[
												"bold",
												true
											],
											[
												"italic",
												true
											],
											[
												"color",
												true
											],
											[
												"horizontal-alignment",
												true
											],
											[
												"vertical-alignment",
												true
											],
											[
												"wrapping",
												true
											],
											[
												"initially-visible",
												true
											],
											[
												"origin",
												true
											]
										]
									}
								]
							},
							{
								"id": "instance-variable",
								"component": [
									{
										"key": "instance-variable",
										"state": []
									}
								]
							},
							{
								"id": "behavior",
								"component": []
							},
							{
								"id": "effect",
								"component": []
							},
							{
								"id": "world-instance",
								"component": [
									{
										"key": "world-instance",
										"state": [
											[
												"x",
												false
											],
											[
												"y",
												false
											],
											[
												"z",
												true
											],
											[
												"w",
												true
											],
											[
												"h",
												true
											],
											[
												"a",
												true
											],
											[
												"o",
												true
											],
											[
												"c",
												true
											],
											[
												"sx",
												true
											],
											[
												"sy",
												true
											],
											[
												"bm",
												true
											],
											[
												"twpx",
												true
											],
											[
												"twpy",
												true
											],
											[
												"twpz",
												true
											],
											[
												"twpw",
												true
											],
											[
												"twph",
												true
											],
											[
												"twpa",
												true
											],
											[
												"dwp",
												true
											],
											[
												"ssm",
												true
											]
										]
									}
								]
							}
						]
					},
					"world": {
						"x": 68.88807628204722,
						"y": 94.54448278800382,
						"width": 20.666231527337175,
						"height": 19.90276660727948,
						"originX": 0,
						"originY": 0,
						"color": [
							1,
							1,
							1,
							1
						],
						"angle": 0,
						"zElevation": 0
					}
				},
				{
					"type": "txt_level_num",
					"properties": {
						"text": "2",
						"enable-bbcode": true,
						"font": "Capture_it",
						"size": 12,
						"line-height": 0,
						"bold": true,
						"italic": false,
						"color": [
							0.6666666666666666,
							0.6666666666666666,
							0.6666666666666666,
							1
						],
						"horizontal-alignment": "center",
						"vertical-alignment": "center",
						"wrapping": "word",
						"initially-visible": true,
						"origin": "top-left"
					},
					"uid": 187,
					"instanceVariables": {},
					"behaviors": {},
					"template": {
						"mode": "replica",
						"templateName": "",
						"sourceTemplateName": "",
						"components": [
							{
								"id": "plugin",
								"component": [
									{
										"key": "plugin",
										"state": [
											[
												"text",
												true
											],
											[
												"enable-bbcode",
												true
											],
											[
												"font",
												true
											],
											[
												"size",
												true
											],
											[
												"line-height",
												true
											],
											[
												"bold",
												true
											],
											[
												"italic",
												true
											],
											[
												"color",
												true
											],
											[
												"horizontal-alignment",
												true
											],
											[
												"vertical-alignment",
												true
											],
											[
												"wrapping",
												true
											],
											[
												"initially-visible",
												true
											],
											[
												"origin",
												true
											]
										]
									}
								]
							},
							{
								"id": "instance-variable",
								"component": [
									{
										"key": "instance-variable",
										"state": []
									}
								]
							},
							{
								"id": "behavior",
								"component": []
							},
							{
								"id": "effect",
								"component": []
							},
							{
								"id": "world-instance",
								"component": [
									{
										"key": "world-instance",
										"state": [
											[
												"x",
												false
											],
											[
												"y",
												false
											],
											[
												"z",
												true
											],
											[
												"w",
												true
											],
											[
												"h",
												true
											],
											[
												"a",
												true
											],
											[
												"o",
												true
											],
											[
												"c",
												true
											],
											[
												"sx",
												true
											],
											[
												"sy",
												true
											],
											[
												"bm",
												true
											],
											[
												"twpx",
												true
											],
											[
												"twpy",
												true
											],
											[
												"twpz",
												true
											],
											[
												"twpw",
												true
											],
											[
												"twph",
												true
											],
											[
												"twpa",
												true
											],
											[
												"dwp",
												true
											],
											[
												"ssm",
												true
											]
										]
									}
								]
							}
						]
					},
					"world": {
						"x": 280.85998566170565,
						"y": 287.83193634154634,
						"width": 20.666231527337175,
						"height": 19.90276660727948,
						"originX": 0,
						"originY": 0,
						"color": [
							1,
							1,
							1,
							1
						],
						"angle": 0,
						"zElevation": 0
					}
				},
				{
					"type": "txt_level_num",
					"properties": {
						"text": "3",
						"enable-bbcode": true,
						"font": "Capture_it",
						"size": 12,
						"line-height": 0,
						"bold": true,
						"italic": false,
						"color": [
							0.6666666666666666,
							0.6666666666666666,
							0.6666666666666666,
							1
						],
						"horizontal-alignment": "center",
						"vertical-alignment": "center",
						"wrapping": "word",
						"initially-visible": true,
						"origin": "top-left"
					},
					"uid": 188,
					"instanceVariables": {},
					"behaviors": {},
					"world": {
						"x": 218.09075019746263,
						"y": 626.9088523759527,
						"width": 20.666231527337175,
						"height": 19.90276660727948,
						"originX": 0,
						"originY": 0,
						"color": [
							1,
							1,
							1,
							1
						],
						"angle": 0,
						"zElevation": 0
					}
				},
				{
					"type": "txt_level_num",
					"properties": {
						"text": "4",
						"enable-bbcode": true,
						"font": "Capture_it",
						"size": 12,
						"line-height": 0,
						"bold": true,
						"italic": false,
						"color": [
							0.6666666666666666,
							0.6666666666666666,
							0.6666666666666666,
							1
						],
						"horizontal-alignment": "center",
						"vertical-alignment": "center",
						"wrapping": "word",
						"initially-visible": true,
						"origin": "top-left"
					},
					"uid": 189,
					"instanceVariables": {},
					"behaviors": {},
					"world": {
						"x": 80.86002791681295,
						"y": 865.6780749289134,
						"width": 20.666231527337175,
						"height": 19.90276660727948,
						"originX": 0,
						"originY": 0,
						"color": [
							1,
							1,
							1,
							1
						],
						"angle": 0,
						"zElevation": 0
					}
				},
				{
					"type": "txt_level_num",
					"properties": {
						"text": "COMING SOON",
						"enable-bbcode": true,
						"font": "Capture_it",
						"size": 12,
						"line-height": 0,
						"bold": true,
						"italic": false,
						"color": [
							0.6666666666666666,
							0.6666666666666666,
							0.6666666666666666,
							1
						],
						"horizontal-alignment": "center",
						"vertical-alignment": "center",
						"wrapping": "word",
						"initially-visible": true,
						"origin": "top-left"
					},
					"uid": 190,
					"instanceVariables": {},
					"behaviors": {},
					"world": {
						"x": 268.5522792689773,
						"y": 1135.216576374978,
						"width": 65.58933662048634,
						"height": 60.518177045230395,
						"originX": 0,
						"originY": 0,
						"color": [
							1,
							1,
							1,
							1
						],
						"angle": 0,
						"zElevation": 0
					}
				}
			],
			"sid": 178953265692254,
			"effectTypes": [],
			"isInitiallyVisible": true,
			"isInitiallyInteractive": true,
			"color": [
				1,
				1,
				1,
				1
			],
			"backgroundColor": [
				1,
				1,
				1,
				1
			],
			"isTransparent": true,
			"parallaxX": 1,
			"parallaxY": 1,
			"scaleRate": 1,
			"forceOwnTexture": false,
			"renderingMode": "3d",
			"drawOrder": "z-order",
			"useRenderCells": false,
			"blendMode": "normal",
			"zElevation": 0,
			"global": false
		},
		{
			"name": "buttons",
			"overriden": 0,
			"subLayers": [],
			"instances": [
				{
					"type": "btn_quit",
					"properties": {
						"initially-visible": true,
						"initial-animation": "Animation 1",
						"initial-frame": 0,
						"enable-collisions": true,
						"live-preview": false
					},
					"uid": 192,
					"instanceVariables": {},
					"behaviors": {},
					"world": {
						"x": 355,
						"y": 8,
						"width": 132.44,
						"height": 52.14,
						"originX": 1,
						"originY": 0,
						"color": [
							1,
							1,
							1,
							1
						],
						"angle": 0,
						"zElevation": 0
					}
				},
				{
					"type": "txt_quit",
					"properties": {
						"text": "QUIT",
						"enable-bbcode": true,
						"font": "Arial",
						"size": 20,
						"line-height": 0,
						"bold": false,
						"italic": false,
						"color": [
							1,
							1,
							1,
							1
						],
						"horizontal-alignment": "center",
						"vertical-alignment": "center",
						"wrapping": "word",
						"initially-visible": true,
						"origin": "center"
					},
					"uid": 193,
					"instanceVariables": {},
					"behaviors": {},
					"world": {
						"x": 287,
						"y": 35,
						"width": 102,
						"height": 66,
						"originX": 0.5,
						"originY": 0.5,
						"color": [
							1,
							1,
							1,
							1
						],
						"angle": 0,
						"zElevation": 0
					}
				}
			],
			"sid": 986533661741909,
			"effectTypes": [],
			"isInitiallyVisible": true,
			"isInitiallyInteractive": true,
			"color": [
				1,
				1,
				1,
				1
			],
			"backgroundColor": [
				1,
				1,
				1,
				1
			],
			"isTransparent": true,
			"parallaxX": 1,
			"parallaxY": 1,
			"scaleRate": 1,
			"forceOwnTexture": false,
			"renderingMode": "3d",
			"drawOrder": "z-order",
			"useRenderCells": false,
			"blendMode": "normal",
			"zElevation": 0,
			"global": false
		},
		{
			"name": "fade",
			"overriden": 0,
			"subLayers": [],
			"instances": [
				{
					"type": "tile_fade",
					"properties": {
						"initially-visible": true,
						"origin": "top-left",
						"wrap-horizontal": "repeat",
						"wrap-vertical": "repeat",
						"image-offset-x": 0,
						"image-offset-y": 0,
						"image-scale-x": 1,
						"image-scale-y": 1,
						"image-angle": 0
					},
					"uid": 191,
					"instanceVariables": {},
					"behaviors": {
						"Tween": {
							"properties": {
								"enabled": true
							}
						}
					},
					"world": {
						"x": -0.11521126673778781,
						"y": -0.9517526947535089,
						"width": 360,
						"height": 640,
						"originX": 0,
						"originY": 0,
						"color": [
							1,
							1,
							1,
							1
						],
						"angle": 0,
						"zElevation": 0
					}
				}
			],
			"sid": 181848525537196,
			"effectTypes": [],
			"isInitiallyVisible": true,
			"isInitiallyInteractive": true,
			"color": [
				1,
				1,
				1,
				1
			],
			"backgroundColor": [
				1,
				1,
				1,
				1
			],
			"isTransparent": true,
			"parallaxX": 0,
			"parallaxY": 0,
			"scaleRate": 1,
			"forceOwnTexture": false,
			"renderingMode": "3d",
			"drawOrder": "z-order",
			"useRenderCells": false,
			"blendMode": "normal",
			"zElevation": 0,
			"global": false
		}
	],
	"sid": 255209707773064,
	"nonworld-instances": [],
	"effectTypes": [],
	"width": 360,
	"height": 1280,
	"unboundedScrolling": false,
	"vpX": 0.5,
	"vpY": 0.5,
	"projection": "perspective",
	"eventSheet": "e_map"
}